[
  {
    "id": 5,
    "name": "Java",
    "ident": "Java",
    "detail": null,
    "parent_id": 1,
    "order": 1,
    "created_at": "2013-08-01T22:39:56+08:00",
    "updated_at": "2013-08-01T22:39:56+08:00",
    "projects_count": 1433510,
    "codes_order": 1,
    "root_id": 1,
    "name_zh_tw": "",
    "name_en": ""
  },
  {
    "id": 3,
    "name": "JavaScript",
    "ident": "JavaScript",
    "detail": null,
    "parent_id": 1,
    "order": 1,
    "created_at": "2013-08-01T21:55:27+08:00",
    "updated_at": "2017-08-21T18:48:05+08:00",
    "projects_count": 477965,
    "codes_order": 3,
    "root_id": 1,
    "name_zh_tw": "",
    "name_en": ""
  },
  {
    "id": 8,
    "name": "PHP",
    "ident": "PHP",
    "detail": null,
    "parent_id": 1,
    "order": 1,
    "created_at": "2013-08-01T23:01:43+08:00",
    "updated_at": "2017-07-27T19:02:43+08:00",
    "projects_count": 361258,
    "codes_order": 2,
    "root_id": 1,
    "name_zh_tw": "",
    "name_en": ""
  },
  {
    "id": 7,
    "name": "Python",
    "ident": "Python",
    "detail": null,
    "parent_id": 1,
    "order": 1,
    "created_at": "2013-08-01T23:00:55+08:00",
    "updated_at": "2017-09-23T21:22:31+08:00",
    "projects_count": 238308,
    "codes_order": 6,
    "root_id": 1,
    "name_zh_tw": "",
    "name_en": ""
  },
  {
    "id": 11,
    "name": "C#",
    "ident": "csharp",
    "detail": null,
    "parent_id": 1,
    "order": 1,
    "created_at": "2013-08-01T23:04:44+08:00",
    "updated_at": "2017-08-21T18:48:05+08:00",
    "projects_count": 195559,
    "codes_order": 4,
    "root_id": 1,
    "name_zh_tw": "",
    "name_en": ""
  },
  {
    "id": 71,
    "name": "Android",
    "ident": "Android",
    "detail": "Android项目",
    "parent_id": 1,
    "order": 1,
    "created_at": "2015-02-15T12:59:49+08:00",
    "updated_at": "2015-02-15T13:00:17+08:00",
    "projects_count": 175476,
    "codes_order": 45,
    "root_id": 1,
    "name_zh_tw": "",
    "name_en": ""
  },
  {
    "id": 10,
    "name": "Objective-C",
    "ident": "Objective-C",
    "detail": null,
    "parent_id": 1,
    "order": 1,
    "created_at": "2013-08-01T23:04:22+08:00",
    "updated_at": "2017-09-23T21:22:31+08:00",
    "projects_count": 164403,
    "codes_order": 11,
    "root_id": 1,
    "name_zh_tw": "",
    "name_en": ""
  },
  {
    "id": 16,
    "name": "Go",
    "ident": "Go",
    "detail": null,
    "parent_id": 1,
    "order": 1,
    "created_at": "2013-08-01T23:23:10+08:00",
    "updated_at": "2017-09-23T21:22:31+08:00",
    "projects_count": 132110,
    "codes_order": 8,
    "root_id": 1,
    "name_zh_tw": "",
    "name_en": ""
  },
  {
    "id": 12,
    "name": "C++",
    "ident": "cpp",
    "detail": null,
    "parent_id": 1,
    "order": 1,
    "created_at": "2013-08-01T23:14:56+08:00",
    "updated_at": "2017-09-23T21:16:56+08:00",
    "projects_count": 104223,
    "codes_order": 45,
    "root_id": 1,
    "name_zh_tw": "",
    "name_en": ""
  },
  {
    "id": 68,
    "name": "HTML",
    "ident": "Html",
    "detail": "",
    "parent_id": 1,
    "order": 1,
    "created_at": "2015-01-05T10:53:52+08:00",
    "updated_at": "2017-09-23T21:22:31+08:00",
    "projects_count": 90174,
    "codes_order": 12,
    "root_id": 1,
    "name_zh_tw": "",
    "name_en": ""
  },
  {
    "id": 6,
    "name": "C",
    "ident": "C",
    "detail": null,
    "parent_id": 1,
    "order": 1,
    "created_at": "2013-08-01T22:41:43+08:00",
    "updated_at": "2017-09-23T21:16:56+08:00",
    "projects_count": 81446,
    "codes_order": 45,
    "root_id": 1,
    "name_zh_tw": "",
    "name_en": ""
  },
  {
    "id": 69,
    "name": "NodeJS",
    "ident": "NodeJS",
    "detail": "",
    "parent_id": 1,
    "order": 1,
    "created_at": "2015-01-05T11:35:42+08:00",
    "updated_at": "2015-01-05T11:35:42+08:00",
    "projects_count": 64185,
    "codes_order": 45,
    "root_id": 1,
    "name_zh_tw": "",
    "name_en": ""
  },
  {
    "id": 63,
    "name": "Swift",
    "ident": "Swift",
    "detail": "",
    "parent_id": 1,
    "order": 1,
    "created_at": "2014-06-17T10:11:06+08:00",
    "updated_at": "2017-09-23T21:22:31+08:00",
    "projects_count": 35478,
    "codes_order": 18,
    "root_id": 1,
    "name_zh_tw": "",
    "name_en": ""
  },
  {
    "id": 109,
    "name": "其他",
    "ident": "others",
    "detail": "其他",
    "parent_id": 1,
    "order": 83,
    "created_at": "2017-07-27T19:02:43+08:00",
    "updated_at": "2019-11-15T19:08:29+08:00",
    "projects_count": 28792,
    "codes_order": 34,
    "root_id": 0,
    "name_zh_tw": "",
    "name_en": "other"
  },
  {
    "id": 48,
    "name": "TypeScript",
    "ident": "TypeScript",
    "detail": null,
    "parent_id": 1,
    "order": 1,
    "created_at": "2013-09-22T18:43:08+08:00",
    "updated_at": "2017-09-23T21:22:31+08:00",
    "projects_count": 25460,
    "codes_order": 14,
    "root_id": 1,
    "name_zh_tw": "",
    "name_en": ""
  },
  {
    "id": 76,
    "name": "微信",
    "ident": "weixin",
    "detail": "小程序",
    "parent_id": 1,
    "order": 2,
    "created_at": "2016-10-09T16:13:30+08:00",
    "updated_at": "2019-11-15T11:12:57+08:00",
    "projects_count": 24264,
    "codes_order": 45,
    "root_id": 0,
    "name_zh_tw": "",
    "name_en": "wechat"
  },
  {
    "id": 107,
    "name": "HTML/CSS",
    "ident": "html-css",
    "detail": "",
    "parent_id": 1,
    "order": 81,
    "created_at": "2017-07-31T11:05:39+08:00",
    "updated_at": "2017-07-31T18:57:23+08:00",
    "projects_count": 21450,
    "codes_order": 45,
    "root_id": 1,
    "name_zh_tw": "",
    "name_en": ""
  },
  {
    "id": 2,
    "name": "Ruby",
    "ident": "Ruby",
    "detail": null,
    "parent_id": 1,
    "order": 1,
    "created_at": "2013-08-01T21:55:24+08:00",
    "updated_at": "2017-09-23T21:22:31+08:00",
    "projects_count": 20702,
    "codes_order": 7,
    "root_id": 1,
    "name_zh_tw": "",
    "name_en": ""
  },
  {
    "id": 15,
    "name": "Shell",
    "ident": "Shell",
    "detail": null,
    "parent_id": 1,
    "order": 1,
    "created_at": "2013-08-01T23:21:38+08:00",
    "updated_at": "2017-09-23T21:22:31+08:00",
    "projects_count": 14169,
    "codes_order": 15,
    "root_id": 1,
    "name_zh_tw": "",
    "name_en": ""
  },
  {
    "id": 4,
    "name": "CSS",
    "ident": "CSS",
    "detail": null,
    "parent_id": 1,
    "order": 1,
    "created_at": "2013-08-01T21:56:29+08:00",
    "updated_at": "2017-09-23T21:22:31+08:00",
    "projects_count": 10276,
    "codes_order": 13,
    "root_id": 1,
    "name_zh_tw": "",
    "name_en": ""
  },
  {
    "id": 49,
    "name": "Dart",
    "ident": "Dart",
    "detail": null,
    "parent_id": 1,
    "order": 1,
    "created_at": "2013-09-22T18:45:26+08:00",
    "updated_at": "2013-09-22T18:45:26+08:00",
    "projects_count": 10109,
    "codes_order": 45,
    "root_id": 1,
    "name_zh_tw": "",
    "name_en": ""
  },
  {
    "id": 75,
    "name": "Docker",
    "ident": "Docker",
    "detail": "",
    "parent_id": 1,
    "order": 1,
    "created_at": "2016-01-06T14:55:44+08:00",
    "updated_at": "2016-01-06T14:55:44+08:00",
    "projects_count": 8154,
    "codes_order": 45,
    "root_id": 1,
    "name_zh_tw": "",
    "name_en": ""
  },
  {
    "id": 106,
    "name": "C/C++",
    "ident": "c-cpp",
    "detail": "",
    "parent_id": 1,
    "order": 80,
    "created_at": "2017-07-31T11:05:19+08:00",
    "updated_at": "2017-09-23T21:16:56+08:00",
    "projects_count": 7981,
    "codes_order": 5,
    "root_id": 1,
    "name_zh_tw": "",
    "name_en": ""
  },
  {
    "id": 78,
    "name": "Kotlin",
    "ident": "Kotlin",
    "detail": "",
    "parent_id": 1,
    "order": 76,
    "created_at": "2017-05-18T18:00:23+08:00",
    "updated_at": "2017-09-23T21:22:31+08:00",
    "projects_count": 7531,
    "codes_order": 17,
    "root_id": 1,
    "name_zh_tw": "",
    "name_en": ""
  },
  {
    "id": 22,
    "name": "Lua",
    "ident": "Lua",
    "detail": null,
    "parent_id": 1,
    "order": 1,
    "created_at": "2013-08-01T23:48:35+08:00",
    "updated_at": "2017-09-23T21:22:31+08:00",
    "projects_count": 7042,
    "codes_order": 20,
    "root_id": 1,
    "name_zh_tw": "",
    "name_en": ""
  },
  {
    "id": 21,
    "name": "Scala",
    "ident": "Scala",
    "detail": null,
    "parent_id": 1,
    "order": 1,
    "created_at": "2013-08-01T23:40:18+08:00",
    "updated_at": "2017-09-23T21:22:31+08:00",
    "projects_count": 5400,
    "codes_order": 23,
    "root_id": 1,
    "name_zh_tw": "",
    "name_en": ""
  },
  {
    "id": 18,
    "name": "Matlab",
    "ident": "Matlab",
    "detail": null,
    "parent_id": 1,
    "order": 1,
    "created_at": "2013-08-01T23:35:17+08:00",
    "updated_at": "2017-09-23T21:22:31+08:00",
    "projects_count": 4030,
    "codes_order": 27,
    "root_id": 1,
    "name_zh_tw": "",
    "name_en": ""
  },
  {
    "id": 36,
    "name": "Delphi",
    "ident": "Delphi",
    "detail": null,
    "parent_id": 1,
    "order": 1,
    "created_at": "2013-08-05T18:56:34+08:00",
    "updated_at": "2013-08-05T18:56:34+08:00",
    "projects_count": 3097,
    "codes_order": 45,
    "root_id": 1,
    "name_zh_tw": "",
    "name_en": ""
  },
  {
    "id": 79,
    "name": "SQL",
    "ident": "sql",
    "detail": "",
    "parent_id": 1,
    "order": 77,
    "created_at": "2017-06-27T10:17:02+08:00",
    "updated_at": "2017-09-23T21:22:31+08:00",
    "projects_count": 2274,
    "codes_order": 31,
    "root_id": 1,
    "name_zh_tw": "",
    "name_en": ""
  },
  {
    "id": 41,
    "name": "Visual Basic",
    "ident": "Visual Basic",
    "detail": null,
    "parent_id": 1,
    "order": 1,
    "created_at": "2013-08-15T15:45:33+08:00",
    "updated_at": "2017-07-31T18:57:24+08:00",
    "projects_count": 2132,
    "codes_order": 45,
    "root_id": 1,
    "name_zh_tw": "",
    "name_en": ""
  },
  {
    "id": 60,
    "name": "TeX/LaTeX",
    "ident": "tex-latex",
    "detail": "LaTeX（LATEX，音译“拉泰赫”）是一种基于TeX的排版系统，由美国计算机学家莱斯利·兰伯特（Leslie Lamport）在20世纪80年代初期开发，利用这种格式，即使使用者没有排版和程序设计的知识也可以充分发挥由TeX所提供的强大功能，能在几天，甚至几小时内生成很多具有书籍质量的印刷品。对于生成复杂表格和数学公式，这一点表现得尤为突出。因此它非常适用于生成高印刷质量的科技和数学类文档。这个系统同样适用于生成从简单的信件到完整书籍的所有其他种类的文档",
    "parent_id": 1,
    "order": 1,
    "created_at": "2013-12-13T09:50:14+08:00",
    "updated_at": "2016-09-13T15:11:53+08:00",
    "projects_count": 2009,
    "codes_order": 45,
    "root_id": 1,
    "name_zh_tw": "",
    "name_en": ""
  },
  {
    "id": 19,
    "name": "ASP",
    "ident": "ASP",
    "detail": null,
    "parent_id": 1,
    "order": 1,
    "created_at": "2013-08-01T23:38:42+08:00",
    "updated_at": "2017-09-23T21:22:31+08:00",
    "projects_count": 1901,
    "codes_order": 10,
    "root_id": 1,
    "name_zh_tw": "",
    "name_en": ""
  },
  {
    "id": 20,
    "name": "Rust",
    "ident": "Rust",
    "detail": null,
    "parent_id": 1,
    "order": 1,
    "created_at": "2013-08-01T23:39:09+08:00",
    "updated_at": "2017-09-23T21:22:31+08:00",
    "projects_count": 1753,
    "codes_order": 19,
    "root_id": 1,
    "name_zh_tw": "",
    "name_en": ""
  },
  {
    "id": 23,
    "name": "ActionScript",
    "ident": "ActionScript",
    "detail": null,
    "parent_id": 1,
    "order": 1,
    "created_at": "2013-08-01T23:52:11+08:00",
    "updated_at": "2017-09-23T21:22:31+08:00",
    "projects_count": 1620,
    "codes_order": 24,
    "root_id": 1,
    "name_zh_tw": "",
    "name_en": ""
  },
  {
    "id": 35,
    "name": "Groovy",
    "ident": "Groovy",
    "detail": null,
    "parent_id": 1,
    "order": 1,
    "created_at": "2013-08-05T18:44:34+08:00",
    "updated_at": "2017-09-23T21:22:31+08:00",
    "projects_count": 1510,
    "codes_order": 25,
    "root_id": 1,
    "name_zh_tw": "",
    "name_en": ""
  },
  {
    "id": 38,
    "name": "R",
    "ident": "R",
    "detail": null,
    "parent_id": 1,
    "order": 1,
    "created_at": "2013-08-05T19:12:02+08:00",
    "updated_at": "2017-09-23T21:22:31+08:00",
    "projects_count": 1472,
    "codes_order": 29,
    "root_id": 1,
    "name_zh_tw": "",
    "name_en": ""
  },
  {
    "id": 31,
    "name": "Verilog",
    "ident": "Verilog",
    "detail": null,
    "parent_id": 1,
    "order": 1,
    "created_at": "2013-08-05T18:27:39+08:00",
    "updated_at": "2013-08-05T18:27:39+08:00",
    "projects_count": 1443,
    "codes_order": 45,
    "root_id": 1,
    "name_zh_tw": "",
    "name_en": ""
  },
  {
    "id": 25,
    "name": "Erlang",
    "ident": "Erlang",
    "detail": null,
    "parent_id": 1,
    "order": 1,
    "created_at": "2013-08-05T17:47:52+08:00",
    "updated_at": "2017-09-23T21:22:31+08:00",
    "projects_count": 1329,
    "codes_order": 16,
    "root_id": 1,
    "name_zh_tw": "",
    "name_en": ""
  },
  {
    "id": 266,
    "name": "易语言",
    "ident": "epl",
    "detail": "易语言，Easy Programming Language",
    "parent_id": 1,
    "order": 82,
    "created_at": "2019-01-16T18:48:02+08:00",
    "updated_at": "2019-01-16T18:48:28+08:00",
    "projects_count": 945,
    "codes_order": 33,
    "root_id": 0,
    "name_zh_tw": "",
    "name_en": ""
  },
  {
    "id": 105,
    "name": "XML",
    "ident": "xml",
    "detail": "",
    "parent_id": 1,
    "order": 79,
    "created_at": "2017-07-31T11:04:28+08:00",
    "updated_at": "2017-09-23T21:22:31+08:00",
    "projects_count": 799,
    "codes_order": 32,
    "root_id": 1,
    "name_zh_tw": "",
    "name_en": ""
  },
  {
    "id": 17,
    "name": "VimL",
    "ident": "VimL",
    "detail": null,
    "parent_id": 1,
    "order": 1,
    "created_at": "2013-08-01T23:31:26+08:00",
    "updated_at": "2017-09-23T21:22:31+08:00",
    "projects_count": 775,
    "codes_order": 28,
    "root_id": 1,
    "name_zh_tw": "",
    "name_en": ""
  },
  {
    "id": 13,
    "name": "Perl",
    "ident": "Perl",
    "detail": null,
    "parent_id": 1,
    "order": 1,
    "created_at": "2013-08-01T23:15:31+08:00",
    "updated_at": "2017-09-23T21:22:31+08:00",
    "projects_count": 703,
    "codes_order": 9,
    "root_id": 1,
    "name_zh_tw": "",
    "name_en": ""
  },
  {
    "id": 26,
    "name": "Arduino",
    "ident": "Arduino",
    "detail": null,
    "parent_id": 1,
    "order": 1,
    "created_at": "2013-08-05T17:55:35+08:00",
    "updated_at": "2013-08-05T17:55:35+08:00",
    "projects_count": 654,
    "codes_order": 45,
    "root_id": 1,
    "name_zh_tw": "",
    "name_en": ""
  },
  {
    "id": 24,
    "name": "Assembly",
    "ident": "Assembly",
    "detail": null,
    "parent_id": 1,
    "order": 1,
    "created_at": "2013-08-01T23:55:22+08:00",
    "updated_at": "2017-09-23T21:22:31+08:00",
    "projects_count": 632,
    "codes_order": 21,
    "root_id": 1,
    "name_zh_tw": "",
    "name_en": ""
  },
  {
    "id": 74,
    "name": "QML",
    "ident": "QML",
    "detail": "",
    "parent_id": 1,
    "order": 1,
    "created_at": "2015-08-22T13:32:20+08:00",
    "updated_at": "2015-08-22T13:32:20+08:00",
    "projects_count": 614,
    "codes_order": 45,
    "root_id": 1,
    "name_zh_tw": "",
    "name_en": ""
  },
  {
    "id": 30,
    "name": "FORTRAN",
    "ident": "FORTRAN",
    "detail": null,
    "parent_id": 1,
    "order": 1,
    "created_at": "2013-08-05T18:00:13+08:00",
    "updated_at": "2013-08-05T18:00:13+08:00",
    "projects_count": 563,
    "codes_order": 45,
    "root_id": 1,
    "name_zh_tw": "",
    "name_en": ""
  },
  {
    "id": 70,
    "name": "Pascal",
    "ident": "Pascal",
    "detail": "",
    "parent_id": 1,
    "order": 1,
    "created_at": "2015-01-30T18:47:39+08:00",
    "updated_at": "2017-09-23T21:22:31+08:00",
    "projects_count": 554,
    "codes_order": 22,
    "root_id": 1,
    "name_zh_tw": "",
    "name_en": ""
  },
  {
    "id": 42,
    "name": "PowerShell",
    "ident": "PowerShell",
    "detail": null,
    "parent_id": 1,
    "order": 1,
    "created_at": "2013-09-12T17:33:48+08:00",
    "updated_at": "2013-09-12T17:33:48+08:00",
    "projects_count": 539,
    "codes_order": 45,
    "root_id": 1,
    "name_zh_tw": "",
    "name_en": ""
  },
  {
    "id": 108,
    "name": "汇编",
    "ident": "asm",
    "detail": "",
    "parent_id": 1,
    "order": 82,
    "created_at": "2017-07-31T11:06:50+08:00",
    "updated_at": "2017-07-31T19:00:51+08:00",
    "projects_count": 529,
    "codes_order": 45,
    "root_id": 1,
    "name_zh_tw": "",
    "name_en": ""
  },
  {
    "id": 43,
    "name": "Emacs Lisp",
    "ident": "Emacs Lisp",
    "detail": null,
    "parent_id": 1,
    "order": 1,
    "created_at": "2013-09-22T17:16:22+08:00",
    "updated_at": "2013-09-22T17:16:22+08:00",
    "projects_count": 501,
    "codes_order": 45,
    "root_id": 1,
    "name_zh_tw": "",
    "name_en": ""
  },
  {
    "id": 27,
    "name": "Clojure",
    "ident": "Clojure",
    "detail": null,
    "parent_id": 1,
    "order": 1,
    "created_at": "2013-08-05T17:55:50+08:00",
    "updated_at": "2017-09-23T21:22:31+08:00",
    "projects_count": 480,
    "codes_order": 26,
    "root_id": 1,
    "name_zh_tw": "",
    "name_en": ""
  },
  {
    "id": 9,
    "name": "CoffeeScript",
    "ident": "CoffeeScript",
    "detail": null,
    "parent_id": 1,
    "order": 1,
    "created_at": "2013-08-01T23:02:49+08:00",
    "updated_at": "2013-08-01T23:02:49+08:00",
    "projects_count": 434,
    "codes_order": 45,
    "root_id": 1,
    "name_zh_tw": "",
    "name_en": ""
  },
  {
    "id": 14,
    "name": "AutoHotkey",
    "ident": "AutoHotkey",
    "detail": null,
    "parent_id": 1,
    "order": 1,
    "created_at": "2013-08-01T23:21:15+08:00",
    "updated_at": "2013-08-01T23:21:15+08:00",
    "projects_count": 349,
    "codes_order": 45,
    "root_id": 1,
    "name_zh_tw": "",
    "name_en": ""
  },
  {
    "id": 55,
    "name": "Julia",
    "ident": "Julia",
    "detail": null,
    "parent_id": 1,
    "order": 1,
    "created_at": "2013-09-22T20:23:42+08:00",
    "updated_at": "2013-09-22T20:23:42+08:00",
    "projects_count": 339,
    "codes_order": 45,
    "root_id": 1,
    "name_zh_tw": "",
    "name_en": ""
  },
  {
    "id": 58,
    "name": "VHDL",
    "ident": "VHDL",
    "detail": null,
    "parent_id": 1,
    "order": 1,
    "created_at": "2013-12-03T15:20:46+08:00",
    "updated_at": "2013-12-03T15:20:46+08:00",
    "projects_count": 312,
    "codes_order": 45,
    "root_id": 1,
    "name_zh_tw": "",
    "name_en": ""
  },
  {
    "id": 57,
    "name": "Elixir",
    "ident": "Elixir",
    "detail": null,
    "parent_id": 1,
    "order": 1,
    "created_at": "2013-09-22T20:27:31+08:00",
    "updated_at": "2013-09-22T20:27:31+08:00",
    "projects_count": 285,
    "codes_order": 45,
    "root_id": 1,
    "name_zh_tw": "",
    "name_en": ""
  },
  {
    "id": 40,
    "name": "Haskell",
    "ident": "Haskell",
    "detail": null,
    "parent_id": 1,
    "order": 1,
    "created_at": "2013-08-13T17:14:09+08:00",
    "updated_at": "2013-08-13T17:14:09+08:00",
    "projects_count": 262,
    "codes_order": 45,
    "root_id": 1,
    "name_zh_tw": "",
    "name_en": ""
  },
  {
    "id": 50,
    "name": "M",
    "ident": "M",
    "detail": null,
    "parent_id": 1,
    "order": 1,
    "created_at": "2013-09-22T18:53:47+08:00",
    "updated_at": "2013-09-22T18:53:47+08:00",
    "projects_count": 260,
    "codes_order": 45,
    "root_id": 1,
    "name_zh_tw": "",
    "name_en": ""
  },
  {
    "id": 39,
    "name": "D",
    "ident": "D",
    "detail": null,
    "parent_id": 1,
    "order": 1,
    "created_at": "2013-08-05T19:12:11+08:00",
    "updated_at": "2013-08-05T19:12:11+08:00",
    "projects_count": 259,
    "codes_order": 45,
    "root_id": 1,
    "name_zh_tw": "",
    "name_en": ""
  },
  {
    "id": 104,
    "name": "Lisp",
    "ident": "Lisp",
    "detail": "",
    "parent_id": 1,
    "order": 78,
    "created_at": "2017-07-30T22:19:38+08:00",
    "updated_at": "2017-09-23T21:22:31+08:00",
    "projects_count": 245,
    "codes_order": 30,
    "root_id": 1,
    "name_zh_tw": "",
    "name_en": ""
  },
  {
    "id": 29,
    "name": "Scheme",
    "ident": "Scheme",
    "detail": null,
    "parent_id": 1,
    "order": 1,
    "created_at": "2013-08-05T17:59:59+08:00",
    "updated_at": "2013-08-05T17:59:59+08:00",
    "projects_count": 236,
    "codes_order": 45,
    "root_id": 1,
    "name_zh_tw": "",
    "name_en": ""
  },
  {
    "id": 34,
    "name": "XSLT",
    "ident": "XSLT",
    "detail": null,
    "parent_id": 1,
    "order": 1,
    "created_at": "2013-08-05T18:41:27+08:00",
    "updated_at": "2013-08-05T18:41:27+08:00",
    "projects_count": 214,
    "codes_order": 45,
    "root_id": 1,
    "name_zh_tw": "",
    "name_en": ""
  },
  {
    "id": 28,
    "name": "Common Lisp",
    "ident": "Common Lisp",
    "detail": null,
    "parent_id": 1,
    "order": 1,
    "created_at": "2013-08-05T17:56:46+08:00",
    "updated_at": "2013-08-05T17:56:46+08:00",
    "projects_count": 212,
    "codes_order": 45,
    "root_id": 1,
    "name_zh_tw": "",
    "name_en": ""
  },
  {
    "id": 73,
    "name": "Logos",
    "ident": "Logos",
    "detail": null,
    "parent_id": 1,
    "order": 1,
    "created_at": "2015-06-07T12:28:53+08:00",
    "updated_at": "2015-06-07T12:28:53+08:00",
    "projects_count": 203,
    "codes_order": 45,
    "root_id": 1,
    "name_zh_tw": "",
    "name_en": ""
  },
  {
    "id": 44,
    "name": "Racket",
    "ident": "Racket",
    "detail": null,
    "parent_id": 1,
    "order": 1,
    "created_at": "2013-09-22T17:18:10+08:00",
    "updated_at": "2013-09-22T17:18:10+08:00",
    "projects_count": 194,
    "codes_order": 45,
    "root_id": 1,
    "name_zh_tw": "",
    "name_en": ""
  },
  {
    "id": 65,
    "name": "DOT",
    "ident": "DOT",
    "detail": null,
    "parent_id": 1,
    "order": 1,
    "created_at": "2014-09-17T22:08:24+08:00",
    "updated_at": "2014-09-17T22:08:24+08:00",
    "projects_count": 194,
    "codes_order": 45,
    "root_id": 1,
    "name_zh_tw": "",
    "name_en": ""
  },
  {
    "id": 45,
    "name": "OCaml",
    "ident": "OCaml",
    "detail": null,
    "parent_id": 1,
    "order": 1,
    "created_at": "2013-09-22T18:37:42+08:00",
    "updated_at": "2013-09-22T18:37:42+08:00",
    "projects_count": 188,
    "codes_order": 45,
    "root_id": 1,
    "name_zh_tw": "",
    "name_en": ""
  },
  {
    "id": 62,
    "name": "Haxe",
    "ident": "Haxe",
    "detail": null,
    "parent_id": 1,
    "order": 1,
    "created_at": "2014-04-29T16:08:57+08:00",
    "updated_at": "2014-04-29T16:08:57+08:00",
    "projects_count": 184,
    "codes_order": 45,
    "root_id": 1,
    "name_zh_tw": "",
    "name_en": ""
  },
  {
    "id": 72,
    "name": "Coq",
    "ident": "Coq",
    "detail": null,
    "parent_id": 1,
    "order": 1,
    "created_at": "2015-03-20T18:32:56+08:00",
    "updated_at": "2015-03-20T18:32:56+08:00",
    "projects_count": 178,
    "codes_order": 45,
    "root_id": 1,
    "name_zh_tw": "",
    "name_en": ""
  },
  {
    "id": 32,
    "name": "Puppet",
    "ident": "Puppet",
    "detail": null,
    "parent_id": 1,
    "order": 1,
    "created_at": "2013-08-05T18:34:36+08:00",
    "updated_at": "2013-08-05T18:34:36+08:00",
    "projects_count": 176,
    "codes_order": 45,
    "root_id": 1,
    "name_zh_tw": "",
    "name_en": ""
  },
  {
    "id": 46,
    "name": "Vala",
    "ident": "Vala",
    "detail": null,
    "parent_id": 1,
    "order": 1,
    "created_at": "2013-09-22T18:41:21+08:00",
    "updated_at": "2013-09-22T18:41:21+08:00",
    "projects_count": 172,
    "codes_order": 45,
    "root_id": 1,
    "name_zh_tw": "",
    "name_en": ""
  },
  {
    "id": 53,
    "name": "LiveScript",
    "ident": "LiveScript",
    "detail": null,
    "parent_id": 1,
    "order": 1,
    "created_at": "2013-09-22T19:43:29+08:00",
    "updated_at": "2013-09-22T19:43:29+08:00",
    "projects_count": 163,
    "codes_order": 45,
    "root_id": 1,
    "name_zh_tw": "",
    "name_en": ""
  },
  {
    "id": 56,
    "name": "Nemerle",
    "ident": "Nemerle",
    "detail": null,
    "parent_id": 1,
    "order": 1,
    "created_at": "2013-09-22T20:26:49+08:00",
    "updated_at": "2013-09-22T20:26:49+08:00",
    "projects_count": 154,
    "codes_order": 45,
    "root_id": 1,
    "name_zh_tw": "",
    "name_en": ""
  },
  {
    "id": 67,
    "name": "Prolog",
    "ident": "Prolog",
    "detail": null,
    "parent_id": 1,
    "order": 1,
    "created_at": "2014-10-22T00:16:19+08:00",
    "updated_at": "2014-10-22T00:16:19+08:00",
    "projects_count": 153,
    "codes_order": 45,
    "root_id": 1,
    "name_zh_tw": "",
    "name_en": ""
  },
  {
    "id": 64,
    "name": "Eiffel",
    "ident": "Eiffel",
    "detail": null,
    "parent_id": 1,
    "order": 1,
    "created_at": "2014-06-29T10:02:31+08:00",
    "updated_at": "2014-06-29T10:02:31+08:00",
    "projects_count": 151,
    "codes_order": 45,
    "root_id": 1,
    "name_zh_tw": "",
    "name_en": ""
  },
  {
    "id": 33,
    "name": "Smalltalk",
    "ident": "Smalltalk",
    "detail": null,
    "parent_id": 1,
    "order": 1,
    "created_at": "2013-08-05T18:41:01+08:00",
    "updated_at": "2017-09-23T21:23:19+08:00",
    "projects_count": 149,
    "codes_order": 33,
    "root_id": 1,
    "name_zh_tw": "",
    "name_en": ""
  },
  {
    "id": 61,
    "name": "Standard ML",
    "ident": "Standard ML",
    "detail": null,
    "parent_id": 1,
    "order": 1,
    "created_at": "2014-04-27T14:00:49+08:00",
    "updated_at": "2014-04-27T14:00:49+08:00",
    "projects_count": 148,
    "codes_order": 45,
    "root_id": 1,
    "name_zh_tw": "",
    "name_en": ""
  },
  {
    "id": 66,
    "name": "Scilab",
    "ident": "Scilab",
    "detail": null,
    "parent_id": 1,
    "order": 1,
    "created_at": "2014-10-11T20:10:04+08:00",
    "updated_at": "2014-10-11T20:10:04+08:00",
    "projects_count": 145,
    "codes_order": 45,
    "root_id": 1,
    "name_zh_tw": "",
    "name_en": ""
  },
  {
    "id": 77,
    "name": "Crystal",
    "ident": "Crystal",
    "detail": "Fast as C, slick as Ruby",
    "parent_id": 1,
    "order": 75,
    "created_at": "2017-04-24T17:29:27+08:00",
    "updated_at": "2017-04-24T17:29:27+08:00",
    "projects_count": 145,
    "codes_order": 45,
    "root_id": 1,
    "name_zh_tw": "",
    "name_en": ""
  },
  {
    "id": 37,
    "name": "eC",
    "ident": "eC",
    "detail": null,
    "parent_id": 1,
    "order": 1,
    "created_at": "2013-08-05T19:01:09+08:00",
    "updated_at": "2013-08-05T19:01:09+08:00",
    "projects_count": 143,
    "codes_order": 45,
    "root_id": 1,
    "name_zh_tw": "",
    "name_en": ""
  },
  {
    "id": 47,
    "name": "Ada",
    "ident": "Ada",
    "detail": null,
    "parent_id": 1,
    "order": 1,
    "created_at": "2013-09-22T18:42:13+08:00",
    "updated_at": "2013-09-22T18:42:13+08:00",
    "projects_count": 142,
    "codes_order": 45,
    "root_id": 1,
    "name_zh_tw": "",
    "name_en": ""
  },
  {
    "id": 54,
    "name": "Slash",
    "ident": "Slash",
    "detail": null,
    "parent_id": 1,
    "order": 1,
    "created_at": "2013-09-22T19:57:31+08:00",
    "updated_at": "2013-09-22T19:57:31+08:00",
    "projects_count": 140,
    "codes_order": 45,
    "root_id": 1,
    "name_zh_tw": "",
    "name_en": ""
  },
  {
    "id": 268,
    "name": "Pawn",
    "ident": "Pawn",
    "detail": "PAWN，曾被称为SMALL，是一种开源的嵌入式脚本语言，最早由荷兰一家名为CompuPhase的公司开发。它的第一个版本于1998年问世，在2005年3月前的版本都被称作SMALL。",
    "parent_id": 1,
    "order": 85,
    "created_at": "2019-03-07T16:29:59+08:00",
    "updated_at": "2019-03-07T16:30:13+08:00",
    "projects_count": 139,
    "codes_order": 1,
    "root_id": 0,
    "name_zh_tw": "",
    "name_en": ""
  },
  {
    "id": 267,
    "name": "Zephir",
    "ident": "Zephir",
    "detail": "一个开源的用于简化PHP扩展的创建和维护，专门给PHP写底层拓展的静态类PHP语言。 http://zephir-lang.com/",
    "parent_id": 1,
    "order": 85,
    "created_at": "2019-03-07T14:46:39+08:00",
    "updated_at": "2019-04-15T15:11:05+08:00",
    "projects_count": 134,
    "codes_order": 1,
    "root_id": 1,
    "name_zh_tw": "",
    "name_en": ""
  },
  {
    "id": 52,
    "name": "Awk",
    "ident": "Awk",
    "detail": null,
    "parent_id": 1,
    "order": 1,
    "created_at": "2013-09-22T19:01:18+08:00",
    "updated_at": "2013-09-22T19:01:18+08:00",
    "projects_count": 134,
    "codes_order": 45,
    "root_id": 1,
    "name_zh_tw": "",
    "name_en": ""
  },
  {
    "id": 51,
    "name": "ColdFusion",
    "ident": "ColdFusion",
    "detail": null,
    "parent_id": 1,
    "order": 1,
    "created_at": "2013-09-22T18:57:39+08:00",
    "updated_at": "2013-09-22T18:57:39+08:00",
    "projects_count": 127,
    "codes_order": 45,
    "root_id": 1,
    "name_zh_tw": "",
    "name_en": ""
  }
]